poker_ai/__init__.py
poker_ai/ai/__init__.py
poker_ai/ai/agent.py
poker_ai/ai/ai.py
poker_ai/ai/runner.py
poker_ai/ai/multiprocess/__init__.py
poker_ai/ai/multiprocess/server.py
poker_ai/ai/multiprocess/worker.py
poker_ai/ai/singleprocess/__init__.py
poker_ai/ai/singleprocess/train.py
poker_ai/cli/__init__.py
poker_ai/cli/runner.py
poker_ai/clustering/__init__.py
poker_ai/clustering/card_combos.py
poker_ai/clustering/card_info_lut_builder.py
poker_ai/clustering/game_utility.py
poker_ai/clustering/preflop.py
poker_ai/clustering/runner.py
poker_ai/games/__init__.py
poker_ai/games/short_deck/__init__.py
poker_ai/games/short_deck/player.py
poker_ai/games/short_deck/state.py
poker_ai/poker/__init__.py
poker_ai/poker/actions.py
poker_ai/poker/card.py
poker_ai/poker/dealer.py
poker_ai/poker/deck.py
poker_ai/poker/engine.py
poker_ai/poker/player.py
poker_ai/poker/pot.py
poker_ai/poker/random_player.py
poker_ai/poker/state.py
poker_ai/poker/table.py
poker_ai/poker/evaluation/__init__.py
poker_ai/poker/evaluation/eval_card.py
poker_ai/poker/evaluation/evaluator.py
poker_ai/poker/evaluation/lookup.py
poker_ai/terminal/__init__.py
poker_ai/terminal/render.py
poker_ai/terminal/results.py
poker_ai/terminal/runner.py
poker_ai/terminal/ascii_objects/__init__.py
poker_ai/terminal/ascii_objects/card_collection.py
poker_ai/terminal/ascii_objects/logger.py
poker_ai/terminal/ascii_objects/player.py
poker_ai/utils/__init__.py
poker_ai/utils/algos.py
poker_ai/utils/debug.py
poker_ai/utils/io.py
poker_ai/utils/logging.py
poker_ai/utils/random.py
poker_ai-1.0.0rc3.data/scripts/poker_ai
test/__init__.py
test/functional/__init__.py
test/functional/test_cli.py
test/functional/test_clustering.py
test/functional/test_engine.py
test/functional/test_evaluator.py
test/functional/test_payouts.py
test/functional/test_short_deck.py
test/unit/__init__.py
test/unit/test_card.py
test/unit/test_dealer.py
test/unit/test_import.py
poker_ai-1.0.0rc3.dist-info/LICENSE
poker_ai-1.0.0rc3.dist-info/METADATA
poker_ai-1.0.0rc3.dist-info/WHEEL
poker_ai-1.0.0rc3.dist-info/top_level.txt
poker_ai-1.0.0rc3.dist-info/RECORD
