Metadata-Version: 2.1
Name: poker-ai
Version: 1.0.0rc3
Summary: Open source implementation of a CFR based poker AI player.
Home-page: https://github.com/fedden/poker_ai
Author: Leon Fedden, Colin Manko
Author-email: leonfedden@gmail.com
License: UNKNOWN
Platform: UNKNOWN
Classifier: Programming Language :: Python :: 3
Classifier: License :: OSI Approved :: GNU General Public License v3 or later (GPLv3+)
Classifier: Operating System :: OS Independent
Requires-Python: >=3.7
Requires-Dist: blessed (==1.17.5)
Requires-Dist: click (==7.0)
Requires-Dist: dill (==0.3.1.1)
Requires-Dist: enlighten (==1.5.2)
Requires-Dist: ipdb (==0.12.3)
Requires-Dist: matplotlib (==3.1.3)
Requires-Dist: numpy (==1.17.4)
Requires-Dist: pytest (==5.4.3)
Requires-Dist: PyYAML (==5.3.1)
Requires-Dist: rich (==1.0.0)
Requires-Dist: recommonmark (==0.6.0)
Requires-Dist: scikit-learn (==0.22.1)
Requires-Dist: scipy (==1.4.1)
Requires-Dist: Sphinx (==3.0.4)
Requires-Dist: sphinx-rtd-theme (==0.4.3)
Requires-Dist: tqdm (==4.43.0)
